{
  "main": {
    "id": "bb26c02fa91ef916",
    "type": "split",
    "children": [
      {
        "id": "4af1db98f57d9f1c",
        "type": "tabs",
        "children": [
          {
            "id": "ff42a698a61e8939",
            "type": "leaf",
            "pinned": true,
            "state": {
              "type": "markdown",
              "state": {
                "file": "Notes/Adventure Notebook.md",
                "mode": "source",
                "source": false
              },
              "pinned": true,
              "icon": "lucide-file",
              "title": "Adventure Notebook"
            }
          }
        ]
      }
    ],
    "direction": "vertical"
  },
  "left": {
    "id": "368707675b62a5f0",
    "type": "split",
    "children": [
      {
        "id": "239a043898fe6d41",
        "type": "tabs",
        "children": [
          {
            "id": "d4649e61769a964d",
            "type": "leaf",
            "state": {
              "type": "file-explorer",
              "state": {
                "sortOrder": "alphabetical",
                "autoReveal": false
              },
              "icon": "lucide-folder-closed",
              "title": "Files"
            }
          },
          {
            "id": "579ff30d42e99a3a",
            "type": "leaf",
            "state": {
              "type": "search",
              "state": {
                "query": "tag:#Waterford",
                "matchingCase": false,
                "explainSearch": false,
                "collapseAll": false,
                "extraContext": false,
                "sortOrder": "alphabetical"
              },
              "icon": "lucide-search",
              "title": "Search"
            }
          },
          {
            "id": "b62b070c5aed4dc1",
            "type": "leaf",
            "state": {
              "type": "bookmarks",
              "state": {},
              "icon": "lucide-bookmark",
              "title": "Bookmarks"
            }
          }
        ]
      }
    ],
    "direction": "horizontal",
    "width": 200
  },
  "right": {
    "id": "09270a4bdb7c98ae",
    "type": "split",
    "children": [
      {
        "id": "8a2291fd238ecbd3",
        "type": "tabs",
        "children": [
          {
            "id": "a26b6017049d26e8",
            "type": "leaf",
            "state": {
              "type": "tag",
              "state": {
                "sortOrder": "frequency",
                "useHierarchy": true,
                "showSearch": false,
                "searchQuery": ""
              },
              "icon": "lucide-tags",
              "title": "Tags"
            }
          },
          {
            "id": "6ba5034cf44964f4",
            "type": "leaf",
            "state": {
              "type": "outline",
              "state": {
                "file": "Notes/Adventure Notebook.md",
                "followCursor": false,
                "showSearch": false,
                "searchQuery": ""
              },
              "icon": "lucide-list",
              "title": "Outline of Adventure Notebook"
            }
          },
          {
            "id": "d78ae6a44d74323e",
            "type": "leaf",
            "state": {
              "type": "backlink",
              "state": {
                "file": "Notes/Adventure Notebook.md",
                "collapseAll": false,
                "extraContext": false,
                "sortOrder": "alphabetical",
                "showSearch": false,
                "searchQuery": "",
                "backlinkCollapsed": false,
                "unlinkedCollapsed": true
              },
              "icon": "links-coming-in",
              "title": "Backlinks for Adventure Notebook"
            }
          },
          {
            "id": "8ca3f60f90941816",
            "type": "leaf",
            "state": {
              "type": "outgoing-link",
              "state": {
                "file": "Notes/Adventure Notebook.md",
                "linksCollapsed": false,
                "unlinkedCollapsed": true
              },
              "icon": "links-going-out",
              "title": "Outgoing links from Adventure Notebook"
            }
          },
          {
            "id": "bd3c7e417a7a78f3",
            "type": "leaf",
            "state": {
              "type": "outline",
              "state": {
                "file": "Notes/Adventure Notebook.md",
                "followCursor": false,
                "showSearch": false,
                "searchQuery": ""
              },
              "icon": "lucide-list",
              "title": "Outline of Adventure Notebook"
            }
          }
        ],
        "currentTab": 1
      }
    ],
    "direction": "horizontal",
    "width": 300
  },
  "left-ribbon": {
    "hiddenItems": {
      "bases:Create new base": false,
      "switcher:Open quick switcher": false,
      "graph:Open graph view": false,
      "canvas:Create new canvas": false,
      "daily-notes:Open today's daily note": false,
      "templates:Insert template": false,
      "command-palette:Open command palette": false,
      "obsidian-importer:Open Importer": false
    }
  },
  "active": "d4649e61769a964d",
  "lastOpenFiles": [
    "Untitled 3.base",
    "Notes/Adventure Notebook.md",
    "Untitled 2.base",
    "Untitled 1.base",
    "Images/world_map_drawing.png",
    "Images/wavesong_intro.png",
    "World/Aepiero Isles.md",
    "Wavesong Shopping List.md",
    "Untitled.base",
    "Ruleset.md",
    "Untitled.canvas",
    "Lore/Gabeto Acunta.md",
    "Images/job_offer_in_a_bottle.png",
    "Images/B7UPAs40Sk.png",
    "Images/faro_encounter.png",
    "Images/faro.png",
    "Images/echo.png",
    "Images/chart_of_spices.png",
    "Images/ancient_star_symbols.png",
    "Images/azami.png",
    "Lore/Fruit Leshy Powers.md",
    "Lore/Captain Kid.md",
    "Lore/Wavesong Intro.md",
    "Campaign Characters/Wavesong.md",
    "Frem.md",
    "Campaign Characters/Faro.md",
    "Campaign Characters/Echo.md",
    "Campaign Characters/Azami.md",
    "Factions/Infury People.md",
    "HTML import/CampaignNotebook.md",
    "World/Midlandia/Pelican Bay.md",
    "Sessions/Session 2.md",
    "Sessions/Session 1.md",
    "World/World.md",
    "World/Midlandia/Midlandia.md",
    "World/Midlandia/Vedmare.md",
    "Lore/Lake Superior.md",
    "Lore/Misc.md",
    "Lore/Shilonia.md",
    "Lore/Pelican Bay.md",
    "Sessions",
    "Quests",
    "Factions",
    "template",
    "World",
    "Images"
  ]
}